ssh_config/__init__.py
ssh_config/cli.py
ssh_config/client.py
ssh_config/errors.py
ssh_config/keywords.py
ssh_config/version.py
ssh_config/commands/__init__.py
ssh_config/commands/base.py
ssh_config/commands/commands.py
ssh_config/commands/ping.py
ssh_config/commands/utils.py
ssh_config-0.1.6.dist-info/licenses/LICENSE
ssh_config-0.1.6.dist-info/METADATA
ssh_config-0.1.6.dist-info/WHEEL
ssh_config-0.1.6.dist-info/entry_points.txt
ssh_config-0.1.6.dist-info/top_level.txt
ssh_config-0.1.6.dist-info/RECORD
