Metadata-Version: 2.4
Name: ssh-config
Version: 0.1.6
Home-page: https://github.com/haginara/ssh_config
Author: Jonghak Choi
Author-email: haginara@gmail.com
License-Expression: MIT
Requires-Python: ~=3.9
License-File: LICENSE
Requires-Dist: pyparsing
Requires-Dist: texttable
Requires-Dist: Jinja2
Requires-Dist: click
Requires-Dist: paramiko
Dynamic: author
Dynamic: author-email
Dynamic: home-page
Dynamic: license-file
